Metadata-Version: 2.1
Name: l2hmc
Version: 0.13.0
Summary: Framework for training MCMC samplers for Lattice QCD
Project-URL: Homepage, https://github.com/saforem2/l2hmc-qcd
Project-URL: Documentation, https://github.com/saforem2/l2hmc-qcd
Project-URL: Issues, https://github.com/saforem2/l2hmc-qcd/issues
Project-URL: Source, https://github.com/saforem2/l2hmc-qcd
Author-email: Sam Foreman <saforem2@gmail.com>
License-File: LICENSE
Classifier: Development Status :: 4 - Beta
Classifier: Programming Language :: Python
Classifier: Programming Language :: Python :: 3.8
Classifier: Programming Language :: Python :: 3.9
Classifier: Programming Language :: Python :: 3.10
Classifier: Programming Language :: Python :: Implementation :: CPython
Classifier: Programming Language :: Python :: Implementation :: PyPy
Requires-Python: >=3.8
Requires-Dist: accelerate
Requires-Dist: arviz
Requires-Dist: bokeh
Requires-Dist: celerite
Requires-Dist: h5py
Requires-Dist: horovod[pytorch,tensorflow]
Requires-Dist: hydra-colorlog
Requires-Dist: hydra-core
Requires-Dist: ipython
Requires-Dist: joblib
Requires-Dist: matplotx
Requires-Dist: mpi4py
Requires-Dist: neovim
Requires-Dist: nodejs
Requires-Dist: ptipython
Requires-Dist: pynvim
Requires-Dist: pyright
Requires-Dist: rich
Requires-Dist: seaborn
Requires-Dist: tensorflow
Requires-Dist: torch
Requires-Dist: tqdm
Requires-Dist: wandb
Requires-Dist: xarray
